README.md
setup.py
acomm/__init__.py
acomm.egg-info/PKG-INFO
acomm.egg-info/SOURCES.txt
acomm.egg-info/dependency_links.txt
acomm.egg-info/requires.txt
acomm.egg-info/top_level.txt