Metadata-Version: 2.1
Name: acomm
Version: 0.0.1
Summary: async utils
Home-page: https://github.com/JiehuiSun/acomm.git
Author: huihui
Author-email: sunjiehuimail@foxmail.com
License: UNKNOWN
Platform: UNKNOWN
Requires-Python: >=3.9
